{
  "source": "SBS English",
  "generatedAt": "2025-10-16T03:09:19.874060+00:00",
  "count": 24,
  "items": [
    {
      "id": "e5ae3bdaec1094c947d1b23677e47b0c",
      "title": "Trump confirms he authorised covert CIA operations in Venezuela",
      "link": "https://www.sbs.com.au/news/article/trump-venezuela-cia-operations/oknxuv9vy",
      "summary": "Donald Trump said he was \"looking at land now\" after recently targeting alleged drug smuggling boats from Venezuela by sea.",
      "publishedAt": "2025-10-16T00:14:05+00:00",
      "source": "SBS English",
      "fetchedAt": "2025-10-16T03:09:19.873608+00:00"
    },
    {
      "id": "8f0efd57fa8c7d9982c1f7f7d6f077af",
      "title": "Madagascar braces for military rule as coup leader prepares to be sworn in",
      "link": "https://www.sbs.com.au/news/article/madagascar-military-coup-leader-prepares-to-be-sworn-in/urqjyxbr8",
      "summary": "The African Union said it was suspending Madagascar after a coup ousted President Andry Rajoelina.",
      "publishedAt": "2025-10-15T19:45:16+00:00",
      "source": "SBS English",
      "fetchedAt": "2025-10-16T03:09:19.873641+00:00"
    },
    {
      "id": "b5913d8dc348b75c930086e886f61acc",
      "title": "Australian passport power revealed, as the US and UK hit record lows",
      "link": "https://www.sbs.com.au/news/article/australias-passport-power-revealed-as-us-and-the-uk-hit-record-lows/1yssu9bu8",
      "summary": "For the first time in 20 years, the United States' passport has fallen from the top ten most powerful in the world.",
      "publishedAt": "2025-10-15T02:51:58+00:00",
      "source": "SBS English",
      "fetchedAt": "2025-10-16T03:09:19.873667+00:00"
    },
    {
      "id": "ef864187adbe80a5f3efd531333779d0",
      "title": "These Sydneysiders watched as the hostage-detainee swap played out. Then came a call",
      "link": "https://www.sbs.com.au/news/article/those-watching-from-afar-as-the-gaza-ceasefire-plays-out-in-real-time/w3ip60rfg",
      "summary": "Palestinian and Jewish Australians describe their emotional journey watching the first phase of the Gaza ceasefire.",
      "publishedAt": "2025-10-15T04:30:43+00:00",
      "source": "SBS English",
      "fetchedAt": "2025-10-16T03:09:19.873686+00:00"
    },
    {
      "id": "ef1723f1e0034dec133ef93803ce7c35",
      "title": "The 'confluence of crises' driving Australia's record-low fertility rate",
      "link": "https://www.sbs.com.au/news/article/the-confluence-of-crises-driving-australias-record-low-fertility-rate/9lh5pvz93",
      "summary": "Australia's birth rate is declining — but researchers say it's \"not about selfishness\".",
      "publishedAt": "2025-10-15T06:53:13+00:00",
      "source": "SBS English",
      "fetchedAt": "2025-10-16T03:09:19.873705+00:00"
    },
    {
      "id": "6bfef285b317b3c02581f45e8cd0bdd0",
      "title": "Afghanistan and Pakistan announce temporary ceasefire following border clashes",
      "link": "https://www.sbs.com.au/news/article/afghanistan-pakistan-ceasefire/odtxselwu",
      "summary": "The truce follows accusations of cross-border attacks and civilian casualties, which have strained relations between the two neighbours.",
      "publishedAt": "2025-10-15T20:55:00+00:00",
      "source": "SBS English",
      "fetchedAt": "2025-10-16T03:09:19.873723+00:00"
    },
    {
      "id": "cb96a966de4ab0d3eef43c7085921580",
      "title": "Labor criticised over worker visa rule backflip that could affect thousands",
      "link": "https://www.sbs.com.au/news/article/labor-criticised-over-worker-visa-rule-backflip-that-could-affect-thousands/i08mdb5c4",
      "summary": "Tens of thousands of people from the Pacific and East Timor currently work in Australia under the PALM scheme.",
      "publishedAt": "2025-10-15T07:12:21+00:00",
      "source": "SBS English",
      "fetchedAt": "2025-10-16T03:09:19.873740+00:00"
    },
    {
      "id": "229c2ceb1c4b11d1ee4a3df1ccba43e5",
      "title": "Kathryn lost her banking job to a chatbot. She just confronted her CBA bosses",
      "link": "https://www.sbs.com.au/news/article/kathryn-lost-her-banking-job-to-a-chatbot-she-just-confronted-her-cba-bosses/cgx8kmymj",
      "summary": "Former Commonwealth Bank employee Kathryn Sullivan spent years teaching the bank's \"Bumblebee\" chatbot how to respond to customers.",
      "publishedAt": "2025-10-15T04:37:46+00:00",
      "source": "SBS English",
      "fetchedAt": "2025-10-16T03:09:19.873772+00:00"
    },
    {
      "id": "d3d44e01ac6e1ec2e5d2181bc22bba7b",
      "title": "'Mystified': Concern for thousands in Australia after Venezuela's surprise move",
      "link": "https://www.sbs.com.au/news/article/venezuela-closes-embassy-australia-maduro-trump/mpgcbcetq",
      "summary": "The closure of Venezuela's embassy in Canberra follows the Nobel Peace Prize being awarded to Venezuela's opposition leader over the weekend. But are the two related?",
      "publishedAt": "2025-10-14T18:35:38+00:00",
      "source": "SBS English",
      "fetchedAt": "2025-10-16T03:09:19.873792+00:00"
    },
    {
      "id": "42000ea24a0a0c3df9b2dd24f138c952",
      "title": "Socceroos' undefeated streak ends with loss to US",
      "link": "https://www.sbs.com.au/news/article/usa-vs-australia-socceroos-undefeated-streak-comes-to-end-with-loss-to-the-united-states/ekybucznm",
      "summary": "The Socceroos have already qualified for the World Cup, with coach Tony Popovic hoping new players \"surprise\" him ahead of the finals.",
      "publishedAt": "2025-10-15T03:04:04+00:00",
      "source": "SBS English",
      "fetchedAt": "2025-10-16T03:09:19.873810+00:00"
    },
    {
      "id": "a80a43d1356dd046a2a1ffda6ff41f2b",
      "title": "US revokes visas of six foreigners over Charlie Kirk comments",
      "link": "https://www.sbs.com.au/news/article/us-revokes-visas-for-six-foreigners-over-charlie-kirk-comments/bccd5ohv8",
      "summary": "According to the US state department, one foreigner whose visa was revoked accused Kirk of spreading \"racist\" rhetoric.",
      "publishedAt": "2025-10-15T03:21:12+00:00",
      "source": "SBS English",
      "fetchedAt": "2025-10-16T03:09:19.873827+00:00"
    },
    {
      "id": "ea541d4e72d7cfc7c0fb721895f9314a",
      "title": "Aboriginal deaths in custody in NSW have reached a record high",
      "link": "https://www.sbs.com.au/nitv/article/aboriginal-deaths-in-custody-in-nsw-have-reached-a-record-high/qg0xomwi1",
      "summary": "The NSW coroner announced the grim milestone in a rare public statement, calling it 'profoundly distressing'.",
      "publishedAt": "2025-10-14T23:34:33+00:00",
      "source": "SBS English",
      "fetchedAt": "2025-10-16T03:09:19.873844+00:00"
    },
    {
      "id": "ad47e15910b788f255e8c5db1df3857b",
      "title": "Military seizes power in Madagascar after president flees amid youth protests",
      "link": "https://www.sbs.com.au/news/article/military-seizes-power-in-madagascar-after-president-flees-amid-youth-protests/qvo024061",
      "summary": "Gen Z-driven demonstrations erupted last month over water and power shortages, quickly escalating into an uprising over broader grievances.",
      "publishedAt": "2025-10-15T01:04:18+00:00",
      "source": "SBS English",
      "fetchedAt": "2025-10-16T03:09:19.873860+00:00"
    },
    {
      "id": "3cc4efb77c24cd59b0db077fcfdbbfde",
      "title": "I'm a mother of five and a world champion. I refuse to let trauma define me",
      "link": "https://www.sbs.com.au/news/insight/article/im-a-mother-of-five-and-a-world-champion-i-refuse-to-let-trauma-define-me/xyr4caydj",
      "summary": "Shantelle's story is one of strength. The proud Barkindji and Ngiyampaa woman says some people prefer to see her as a victim.",
      "publishedAt": "2025-10-14T18:36:42+00:00",
      "source": "SBS English",
      "fetchedAt": "2025-10-16T03:09:19.873877+00:00"
    },
    {
      "id": "2cf96ad8654d14a655e6368c6376edf8",
      "title": "'Our shining star has dimmed': Celebrated soul musician D'Angelo dies at 51",
      "link": "https://www.sbs.com.au/news/article/our-shining-star-has-dimmed-celebrated-soul-musician-dangelo-dies-at-51/7vo00osym",
      "summary": "Acclaimed American soul musician D'Angelo has died at 51 after a \"prolonged and courageous battle with cancer\", his family says.",
      "publishedAt": "2025-10-14T19:04:21+00:00",
      "source": "SBS English",
      "fetchedAt": "2025-10-16T03:09:19.873892+00:00"
    },
    {
      "id": "def08fb9ad5ab463bf0d42db63e7ad60",
      "title": "Warning Australia faces 'looming period of risk' as it awaits nuclear submarines",
      "link": "https://www.sbs.com.au/news/article/warning-australia-facing-looming-period-of-risk-as-it-awaits-for-nuclear-submarines/tv9hb3orn",
      "summary": "As Australia awaits nuclear-powered submarines, a strategic policy think tank warns we're sitting vulnerable to potential threats.",
      "publishedAt": "2025-10-14T19:21:38+00:00",
      "source": "SBS English",
      "fetchedAt": "2025-10-16T03:09:19.873907+00:00"
    },
    {
      "id": "d5eb15f8b8a3f072b0df1e231020c4bd",
      "title": "Hamas' next move is unknown, but one person may 'hold the key' to a lasting peace in Gaza",
      "link": "https://www.sbs.com.au/news/article/gaza-peace-deal-what-happens-next/mxbnk7p2v",
      "summary": "The first phase of a deeply complex peace process has begun. So what happens next?",
      "publishedAt": "2025-10-14T06:34:21+00:00",
      "source": "SBS English",
      "fetchedAt": "2025-10-16T03:09:19.873922+00:00"
    },
    {
      "id": "71097ef9451dbe095ea2462511b153a7",
      "title": "Victorian Coalition pledges to tear up Treaty laws if elected in 2026",
      "link": "https://www.sbs.com.au/nitv/article/victorian-coalition-pledges-to-tear-up-treaty-laws-if-elected-in-2026/p31zs17d5",
      "summary": "Victoria’s Opposition has vowed to scrap the state’s landmark Treaty legislation within 100 days if it wins government in 2026 - pledging instead to create a new First Nations department.",
      "publishedAt": "2025-10-14T05:47:01+00:00",
      "source": "SBS English",
      "fetchedAt": "2025-10-16T03:09:19.873938+00:00"
    },
    {
      "id": "2eac2fe44e6429ce92c890c7279de0dd",
      "title": "'The greatest joy': Palestinians reunite with loved ones after Israeli imprisonment",
      "link": "https://www.sbs.com.au/news/article/palestinians-reunite-with-family-after-release-by-israel/91ul3ppe6",
      "summary": "Deeply emotional scenes unfolded in Gaza and the West Bank as Palestinian prisoners and detainees returned after their release by Israel.",
      "publishedAt": "2025-10-13T23:27:44+00:00",
      "source": "SBS English",
      "fetchedAt": "2025-10-16T03:09:19.873955+00:00"
    },
    {
      "id": "0d960bd899656fec9831f257edb63d9b",
      "title": "'Eating mostly brown food': The 'devastating' juggle faced by a rising number of Australians",
      "link": "https://www.sbs.com.au/news/article/juggling-act-social-services-payments-rent-food/g4wjshlw9",
      "summary": "With one in seven Australians living below the poverty line, researchers and advocates say that COVID-era universal income is the solution.",
      "publishedAt": "2025-10-13T18:32:50+00:00",
      "source": "SBS English",
      "fetchedAt": "2025-10-16T03:09:19.873971+00:00"
    },
    {
      "id": "f0b5d82da36d30d788bd2759f48e969a",
      "title": "'Concern' over prime minister and Opposition leader's phone numbers being leaked",
      "link": "https://www.sbs.com.au/news/article/concern-over-prime-ministers-phone-being-leaked/rrh4ae0o5",
      "summary": "Anthony Albanese and Sussan Ley are among dozens of high-profile Australians whose numbers have been leaked.",
      "publishedAt": "2025-10-14T00:55:02+00:00",
      "source": "SBS English",
      "fetchedAt": "2025-10-16T03:09:19.873986+00:00"
    },
    {
      "id": "3a6829e562fdc08a35cfd6712ba3af2e",
      "title": "'The hunt for the nearest mechanic': NATO chief mocks 'broken' Russian submarine",
      "link": "https://www.sbs.com.au/news/article/nato-chief-mocks-broken-russian-submarine/xy1ynrhdh",
      "summary": "Russia's Black Sea Fleet rejected reports the diesel-powered submarine had suffered a serious malfunction.",
      "publishedAt": "2025-10-14T08:10:47+00:00",
      "source": "SBS English",
      "fetchedAt": "2025-10-16T03:09:19.874001+00:00"
    },
    {
      "id": "a29622799582dc1d75a299590aef9681",
      "title": "The common way Australians have their data stolen — and what it's costing",
      "link": "https://www.sbs.com.au/news/article/how-australians-unknowingly-hand-over-their-security-to-hackers/2l7tlnxdq",
      "summary": "The average financial losses from cybercrimes, both for Australians and businesses, continue to rise annually.",
      "publishedAt": "2025-10-13T12:02:02+00:00",
      "source": "SBS English",
      "fetchedAt": "2025-10-16T03:09:19.874020+00:00"
    },
    {
      "id": "54a7898d0ee7ea167b5baaae9799ce52",
      "title": "Has your Qantas data been leaked? Here's what you can do",
      "link": "https://www.sbs.com.au/news/article/what-to-do-if-your-qantas-data-was-leaked/vk1922mpe",
      "summary": "A cybersecurity expert has warned scammers will employ both immediate and \"long game\" strategies to use the stolen data.",
      "publishedAt": "2025-10-13T02:08:16+00:00",
      "source": "SBS English",
      "fetchedAt": "2025-10-16T03:09:19.874035+00:00"
    }
  ]
}